PyHardLinkBackup/__init__.py
PyHardLinkBackup/__main__.py
PyHardLinkBackup/backup.py
PyHardLinkBackup/compare_backup.py
PyHardLinkBackup/constants.py
PyHardLinkBackup/logging_setup.py
PyHardLinkBackup/rebuild_databases.py
PyHardLinkBackup/cli_app/__init__.py
PyHardLinkBackup/cli_app/phlb.py
PyHardLinkBackup/cli_dev/__init__.py
PyHardLinkBackup/cli_dev/__main__.py
PyHardLinkBackup/cli_dev/benchmark.py
PyHardLinkBackup/cli_dev/code_style.py
PyHardLinkBackup/cli_dev/debugging.py
PyHardLinkBackup/cli_dev/packaging.py
PyHardLinkBackup/cli_dev/shell_completion.py
PyHardLinkBackup/cli_dev/testing.py
PyHardLinkBackup/cli_dev/update_readme_history.py
PyHardLinkBackup/tests/__init__.py
PyHardLinkBackup/tests/test_backup.py
PyHardLinkBackup/tests/test_compare_backup.py
PyHardLinkBackup/tests/test_doc_write.py
PyHardLinkBackup/tests/test_doctests.py
PyHardLinkBackup/tests/test_project_setup.py
PyHardLinkBackup/tests/test_readme.py
PyHardLinkBackup/tests/test_readme_history.py
PyHardLinkBackup/tests/test_rebuild_database.py
PyHardLinkBackup/utilities/__init__.py
PyHardLinkBackup/utilities/file_hash_database.py
PyHardLinkBackup/utilities/file_size_database.py
PyHardLinkBackup/utilities/filesystem.py
PyHardLinkBackup/utilities/humanize.py
PyHardLinkBackup/utilities/rich_utils.py
PyHardLinkBackup/utilities/sha256sums.py
PyHardLinkBackup/utilities/tee.py
PyHardLinkBackup/utilities/tyro_cli_shared_args.py
PyHardLinkBackup/utilities/tests/__init__.py
PyHardLinkBackup/utilities/tests/test_file_hash_database.py
PyHardLinkBackup/utilities/tests/test_file_size_database.py
PyHardLinkBackup/utilities/tests/test_filesystem.py
PyHardLinkBackup/utilities/tests/unittest_utilities.py
pyhardlinkbackup-1.8.1.dist-info/METADATA
pyhardlinkbackup-1.8.1.dist-info/WHEEL
pyhardlinkbackup-1.8.1.dist-info/entry_points.txt
pyhardlinkbackup-1.8.1.dist-info/RECORD
