Metadata-Version: 2.4
Name: PyHardLinkBackup
Version: 1.8.1
Summary: HardLink/Deduplication Backups with Python
Project-URL: Documentation, https://github.com/jedie/PyHardLinkBackup
Project-URL: Source, https://github.com/jedie/PyHardLinkBackup
Author-email: Jens Diemer <PyHardLinkBackup@jensdiemer.de>
License: GPL-3.0-or-later
Requires-Python: >=3.12
Requires-Dist: bx-py-utils
Requires-Dist: cli-base-utilities>=0.27.1
Requires-Dist: rich
Requires-Dist: tyro
